{
    "@class": "com.kony.gen.viz.model.component.KVizLabel",
    "DNDConfig": null,
    "__parentReadjusting__": false,
    "_height_": {
        "type": "ref",
        "value": "preferred"
    },
    "_left_": {
        "type": "string",
        "value": "9%"
    },
    "_margin_": [
        1,
        1,
        1,
        1
    ],
    "_padding_": [
        1,
        1,
        1,
        1
    ],
    "_skin_": "s2389b948e51471191cc75878a587063",
    "_text_": "Label",
    "_top_": {
        "type": "string",
        "value": "0dp"
    },
    "_width_": {
        "type": "string",
        "value": "90%"
    },
    "_wrapping_": 2,
    "canUpdateUI": true,
    "containerId": true,
    "containerweight": 100,
    "contentalignment": 4,
    "id": "lblAddressSuggestionKA",
    "info": null,
    "iscustomlayout": false,
    "isvisible": true,
    "kuid": "b98680fbb3c14185847d7d72bb53458f",
    "maxnumberoflines": 1,
    "name": "kony.ui.Label",
    "paddinginpixel": false,
    "parent": "flxMainAddressSuggestions",
    "pf": "tmpAddressSuggestions",
    "retaincontentalignment": false,
    "retainflexpositionproperties": false,
    "textstyle": {},
    "texttruncateposition": 3,
    "tooltip": "",
    "wType": "Label",
    "zindex": 1
}