{
    "AS_TextField_a7417f72dcde4d0a9fedfcb59e997b8d": {
        "actions": [
            {
                "callbackType": null,
                "disabled": null,
                "display": "animateTextPlaceholder",
                "id": "INVOKE_FUNCTION__ide_onBeginEditing_e54d500fe34247978ca557103f361667",
                "inputparams": [
                    {
                        "name": "fieldId",
                        "value": " eventobject"
                    },
                    {
                        "name": "placeholderId",
                        "value": "\"lblCityKA\""
                    }
                ],
                "sequenceKUID": "animateTextPlaceholder",
                "source": "controller",
                "type": "INVOKE_FUNCTION"
            }
        ],
        "id": "AS_TextField_a7417f72dcde4d0a9fedfcb59e997b8d",
        "language": "js",
        "params": [
            {
                "datatype": "collection",
                "name": "eventobject"
            },
            {
                "datatype": "string",
                "name": "changedtext"
            }
        ],
        "type": "ACTION_SEQUENCE"
    }
}